porems/__init__.py
porems/atom.py
porems/database.py
porems/dice.py
porems/generic.py
porems/geometry.py
porems/matrix.py
porems/molecule.py
porems/pattern.py
porems/pore.py
porems/shape.py
porems/store.py
porems/system.py
porems/utils.py
porems/templates/amorph.gro
porems/templates/antechamber.job
porems/templates/antechamber.tleap
porems/templates/grid.itp
porems/templates/topol.top
tests/__init__.py
tests/test_simple.py
porems-0.3.0.dist-info/LICENSE
porems-0.3.0.dist-info/METADATA
porems-0.3.0.dist-info/WHEEL
porems-0.3.0.dist-info/top_level.txt
porems-0.3.0.dist-info/RECORD
