Metadata-Version: 2.1
Name: porems
Version: 0.3.0
Summary: Pore Generator for Molecular Simulations.
Home-page: https://github.com/Ajax23/PoreMS
Author: Hamzeh Kraus
Author-email: kraus@itt.uni-stuttgart.de
Classifier: Programming Language :: Python :: 3
Classifier: License :: OSI Approved :: GNU General Public License v3 (GPLv3)
Classifier: Operating System :: OS Independent
Requires-Python: >=3.5
License-File: LICENSE
Requires-Dist: pandas
Requires-Dist: seaborn
Requires-Dist: pyyaml
